{
  "descriptionHash": "85ADB9BE6D11316DAFBE3B0E8F2F389A9EA7C2C19DA350FF5F79DCBFC4CAAA1967A041F0A65DB290F7C8A88A89E1DEAA4817D96EE12E14E2EAA72F0513AF7590",
  "descriptionLocation": "https://api.sales.createif-labs.de/swagger/v1/swagger.json",
  "lockFileVersion": "1.0.0",
  "kiotaVersion": "1.16.0",
  "clientClassName": "SalesPortalClient",
  "clientNamespaceName": "SalesPortal.Client",
  "language": "CSharp",
  "usesBackingStore": false,
  "excludeBackwardCompatible": false,
  "includeAdditionalData": true,
  "disableSSLValidation": false,
  "serializers": [
    "Microsoft.Kiota.Serialization.Json.JsonSerializationWriterFactory",
    "Microsoft.Kiota.Serialization.Text.TextSerializationWriterFactory",
    "Microsoft.Kiota.Serialization.Form.FormSerializationWriterFactory",
    "Microsoft.Kiota.Serialization.Multipart.MultipartSerializationWriterFactory"
  ],
  "deserializers": [
    "Microsoft.Kiota.Serialization.Json.JsonParseNodeFactory",
    "Microsoft.Kiota.Serialization.Text.TextParseNodeFactory",
    "Microsoft.Kiota.Serialization.Form.FormParseNodeFactory"
  ],
  "structuredMimeTypes": [
    "application/json",
    "text/plain;q=0.9",
    "application/x-www-form-urlencoded;q=0.2",
    "multipart/form-data;q=0.1"
  ],
  "includePatterns": [],
  "excludePatterns": [],
  "disabledValidationRules": []
}